MANIFEST.in
README.md
setup.py
ffmpeg/GPLv3.txt
ffmpeg/ffmpeg
ffmpeg/ffmpeg_sdk.py
ffmpeg/ffprobe
ffmpeg/qt-faststart
ffmpeg/readme.txt
ffmpeg_sdk.egg-info/PKG-INFO
ffmpeg_sdk.egg-info/SOURCES.txt
ffmpeg_sdk.egg-info/dependency_links.txt
ffmpeg_sdk.egg-info/top_level.txt