Metadata-Version: 1.1
Name: ffmpeg-sdk
Version: 4.0.0
Summary: ffmpeg package for heroku
Home-page: http://www.elinkgate.com
Author: Truong Cong Hoan Vu
Author-email: kevin.truong.ds@gmail.com
License: UNKNOWN
Platform: UNKNOWN
Classifier: Programming Language :: Python :: 3
Classifier: License :: OSI Approved :: MIT License
